conan_settings/__init__.py
conan_settings/cli.py
conan_settings-0.1.1.dist-info/LICENSE.txt
conan_settings-0.1.1.dist-info/METADATA
conan_settings-0.1.1.dist-info/WHEEL
conan_settings-0.1.1.dist-info/entry_points.txt
conan_settings-0.1.1.dist-info/top_level.txt
conan_settings-0.1.1.dist-info/RECORD
